pipsource/__init__.py
pipsource/__version__.py
pipsource/cli.py
pipsource/show.py
pipsource/sources.py
pipsource-0.1.1.dist-info/METADATA
pipsource-0.1.1.dist-info/RECORD
pipsource-0.1.1.dist-info/WHEEL
pipsource-0.1.1.dist-info/entry_points.txt
pipsource-0.1.1.dist-info/top_level.txt
