Metadata-Version: 2.1
Name: pipsource
Version: 0.1.1
Summary: manage source of pipenv projects
Home-page: https://github.com/duyixian1234/pipsource
Author: Yixian Du
Author-email: duyixian1234@qq.com
License: MIT
Platform: UNKNOWN
Classifier: License :: OSI Approved :: MIT License
Classifier: Programming Language :: Python
Classifier: Programming Language :: Python :: 3.6
Classifier: Programming Language :: Python :: Implementation :: CPython
Classifier: Programming Language :: Python :: Implementation :: PyPy
Requires-Dist: click
Requires-Dist: pipenv
Requires-Dist: toml
